maxclientapi/__init__.py
maxclientapi/listen_handler.py
maxclientapi/main.py
maxclientapi/send_handshake.py
maxclientapi/start_keepalive.py
maxclientapi-2.7.0.dist-info/LICENSE
maxclientapi-2.7.0.dist-info/METADATA
maxclientapi-2.7.0.dist-info/WHEEL
maxclientapi-2.7.0.dist-info/top_level.txt
maxclientapi-2.7.0.dist-info/RECORD
