Metadata-Version: 2.1
Name: maxclientapi
Version: 2.7.0
Summary: A Python library for working with the 'MAX Messenger' WebSocket API
Home-page: https://github.com/arsrus721/maxclientapi
Author: arsrus721
Classifier: Programming Language :: Python :: 3
Classifier: License :: OSI Approved :: MIT License
License-File: LICENSE
Requires-Dist: websocket-client
